tilsit_config/.mypy_cache/.gitignore
tilsit_config/.mypy_cache/3.13/@plugins_snapshot.json
tilsit_config/.mypy_cache/3.13/_ast.data.json
tilsit_config/.mypy_cache/3.13/_ast.meta.json
tilsit_config/.mypy_cache/3.13/_codecs.data.json
tilsit_config/.mypy_cache/3.13/_codecs.meta.json
tilsit_config/.mypy_cache/3.13/_collections_abc.data.json
tilsit_config/.mypy_cache/3.13/_collections_abc.meta.json
tilsit_config/.mypy_cache/3.13/_frozen_importlib.data.json
tilsit_config/.mypy_cache/3.13/_frozen_importlib.meta.json
tilsit_config/.mypy_cache/3.13/_frozen_importlib_external.data.json
tilsit_config/.mypy_cache/3.13/_frozen_importlib_external.meta.json
tilsit_config/.mypy_cache/3.13/_io.data.json
tilsit_config/.mypy_cache/3.13/_io.meta.json
tilsit_config/.mypy_cache/3.13/_sitebuiltins.data.json
tilsit_config/.mypy_cache/3.13/_sitebuiltins.meta.json
tilsit_config/.mypy_cache/3.13/_typeshed/__init__.data.json
tilsit_config/.mypy_cache/3.13/_typeshed/__init__.meta.json
tilsit_config/.mypy_cache/3.13/_typeshed/importlib.data.json
tilsit_config/.mypy_cache/3.13/_typeshed/importlib.meta.json
tilsit_config/.mypy_cache/3.13/_warnings.data.json
tilsit_config/.mypy_cache/3.13/_warnings.meta.json
tilsit_config/.mypy_cache/3.13/abc.data.json
tilsit_config/.mypy_cache/3.13/abc.meta.json
tilsit_config/.mypy_cache/3.13/ast.data.json
tilsit_config/.mypy_cache/3.13/ast.meta.json
tilsit_config/.mypy_cache/3.13/builtins.data.json
tilsit_config/.mypy_cache/3.13/builtins.meta.json
tilsit_config/.mypy_cache/3.13/codecs.data.json
tilsit_config/.mypy_cache/3.13/codecs.meta.json
tilsit_config/.mypy_cache/3.13/collections/__init__.data.json
tilsit_config/.mypy_cache/3.13/collections/__init__.meta.json
tilsit_config/.mypy_cache/3.13/collections/abc.data.json
tilsit_config/.mypy_cache/3.13/collections/abc.meta.json
tilsit_config/.mypy_cache/3.13/config/__init__.data.json
tilsit_config/.mypy_cache/3.13/config/__init__.meta.json
tilsit_config/.mypy_cache/3.13/config/settings.data.json
tilsit_config-1.0.1.dist-info/WHEEL
tilsit_config-1.0.1.dist-info/METADATA
tilsit_config-1.0.1.dist-info/RECORD
