Metadata-Version: 2.3
Name: tilsit-config
Version: 1.0.1
Summary: Configuration handling
Author: Rafal Padkowski
Author-email: Rafal Padkowski <rafaelp@poczta.onet.pl>
Requires-Dist: tomlkit>=0.13.3
Requires-Python: >=3.13
